mlcommons_box_ssh/__init__.py
mlcommons_box_ssh/__main__.py
mlcommons_box_ssh/platform.yaml.template
mlcommons_box_ssh/ssh_metadata.py
mlcommons_box_ssh/ssh_run.py
mlcommons_box_ssh/utils.py
mlcommons_box_ssh/tests/__init__.py
mlcommons_box_ssh/tests/test_mlcommons_box_singularity_cli.py
mlcommons_box_ssh/tests/test_platform_metadata.py
mlcommons_box_ssh/tests/test_python_interpreters.py
mlcommons_box_ssh/tests/test_data/platforms/platform_01.yaml
mlcommons_box_ssh/tests/test_data/platforms/platform_02.yaml
mlcommons_box_ssh-0.2.3.dist-info/METADATA
mlcommons_box_ssh-0.2.3.dist-info/WHEEL
mlcommons_box_ssh-0.2.3.dist-info/entry_points.txt
mlcommons_box_ssh-0.2.3.dist-info/top_level.txt
mlcommons_box_ssh-0.2.3.dist-info/RECORD
